dojobber/__init__.py
dojobber/__version__.py
dojobber/dojobber.py
dojobber-0.6.2.dist-info/DESCRIPTION.rst
dojobber-0.6.2.dist-info/METADATA
dojobber-0.6.2.dist-info/RECORD
dojobber-0.6.2.dist-info/WHEEL
dojobber-0.6.2.dist-info/metadata.json
dojobber-0.6.2.dist-info/top_level.txt
