Metadata-Version: 2.0
Name: dojobber
Version: 0.6.2
Summary: Job orchestration framework based on individual idempotent python classes and dependencies.
Home-page: https://github.com/ExtraHop/DoJobber
Author: Bri Hatch
Author-email: bri@extrahop.com
License: MIT
Platform: UNKNOWN
Classifier: Development Status :: 4 - Beta
Classifier: Intended Audience :: Developers
Classifier: Topic :: System :: Systems Administration
Classifier: License :: OSI Approved :: MIT License
Classifier: Programming Language :: Python
Requires-Python: >=2.7
Requires-Dist: python-graph-core
Requires-Dist: python-graph-dot
